bumper/__init__.py
bumper/bump.py
bumper/cli.py
bumper/config.py
sco1_bumper-2.0.1.dist-info/METADATA
sco1_bumper-2.0.1.dist-info/WHEEL
sco1_bumper-2.0.1.dist-info/entry_points.txt
sco1_bumper-2.0.1.dist-info/licenses/LICENSE
sco1_bumper-2.0.1.dist-info/RECORD
