Metadata-Version: 2.4
Name: sco1-bumper
Version: 2.0.1
Summary: Automatically increment the project's version number.
Project-URL: Homepage, https://github.com/sco1/
Project-URL: Documentation, https://github.com/sco1/bumper/blob/main/README.md
Project-URL: Repository, https://github.com/sco1/bumper.git
Project-URL: Issues, https://github.com/sco1/bumper/issues
Project-URL: Changelog, https://github.com/sco1/bumper/blob/main/CHANGELOG.md
Author-email: sco1 <sco1.git@gmail.com>
License-Expression: MIT
License-File: LICENSE
Classifier: Development Status :: 5 - Production/Stable
Classifier: Intended Audience :: Developers
Classifier: Operating System :: OS Independent
Classifier: Programming Language :: Python :: 3 :: Only
Classifier: Programming Language :: Python :: 3.11
Classifier: Programming Language :: Python :: 3.12
Classifier: Programming Language :: Python :: 3.13
Classifier: Typing :: Typed
Requires-Python: >=3.11
Requires-Dist: packaging~=25.0
Requires-Dist: typer-slim~=0.12
